{
	"credit": "Made with Blockbench",
	"parent": "minecraft:block/cube_all",
	"texture_size": [32, 16],
	"textures": {
		"particle": "megamanarmormod:block/mysterywaveblue",
		"block": "megamanarmormod:block/mysterywaveblue"
	},
	"elements": [
		{
			"from": [2, 4, 2],
			"to": [14, 12, 14],
			"color": 3,
			"faces": {
				"north": {"uv": [1, 4, 7, 12], "texture": "#block"},
				"east": {"uv": [1, 4, 7, 12], "texture": "#block"},
				"south": {"uv": [1, 4, 7, 12], "texture": "#block"},
				"west": {"uv": [1, 4, 7, 12], "texture": "#block"},
				"up": {"uv": [9, 2, 15, 14], "texture": "#block"},
				"down": {"uv": [9, 2, 15, 14], "texture": "#block"}
			}
		}
	]
}